README.rst
setup.cfg
setup.py
./__init__.py
./carrier.py
./configuration.xml
./party.py
./sale.py
./sale.xml
./shipping_data.xml
./stock.py
./stock.xml
./tryton.cfg
./locale/de_DE.po
./tests/__init__.py
./tests/test_ups.py
./tests/test_views_depends.py
./view/carrier_form.xml
./view/sale_configuration_view_form.xml
./view/sale_view_form.xml
./view/shipment_view_form.xml
./view/shipping_ups_configuration_form.xml
./view/ups_configuration_form.xml
./view/ups_service_form.xml
./view/ups_service_tree.xml
openlabs_shipping_ups.egg-info/PKG-INFO
openlabs_shipping_ups.egg-info/SOURCES.txt
openlabs_shipping_ups.egg-info/dependency_links.txt
openlabs_shipping_ups.egg-info/entry_points.txt
openlabs_shipping_ups.egg-info/not-zip-safe
openlabs_shipping_ups.egg-info/requires.txt
openlabs_shipping_ups.egg-info/top_level.txt